unifsysdisc/__init__.py
unifsysdisc/wsgi.py
unif_sys_disc-0.0.1.dist-info/LICENSE
unif_sys_disc-0.0.1.dist-info/METADATA
unif_sys_disc-0.0.1.dist-info/WHEEL
unif_sys_disc-0.0.1.dist-info/RECORD
