Metadata-Version: 2.1
Name: unif-sys-disc
Version: 0.0.1
Summary: A unified framework for system discovery
Home-page: https://github.com/AutotwinEU/unif-sys-disc
License: BSD-3-Clause
Keywords: production systems,model generation
Author: Lulai Zhu
Author-email: lulai.zhu@gmail.com
Requires-Python: >=3.10,<4.0
Classifier: Development Status :: 1 - Planning
Classifier: Intended Audience :: Manufacturing
Classifier: License :: OSI Approved :: BSD License
Classifier: Operating System :: OS Independent
Classifier: Programming Language :: Python :: 3
Classifier: Programming Language :: Python :: 3.10
Classifier: Programming Language :: Python :: 3.11
Classifier: Programming Language :: Python :: 3.12
Classifier: Programming Language :: Python :: 3 :: Only
Requires-Dist: Flask (>=3.0.2,<4.0.0)
Requires-Dist: Paste (>=3.7.1,<4.0.0)
Requires-Dist: waitress (>=3.0.0,<4.0.0)
